tpcli/__init__.py
tpcli/exceptions.py
tuxput/__init__.py
tuxput/config.py
tuxput/filters.py
tuxput/resources.py
tuxput/static/robots.txt
tuxput/static/styles.css
tuxput/templates/404.html
tuxput/templates/files.html
tuxput/templates/footer.html
tuxput/templates/layout.html
tuxput/templates/root.html
tuxput-0.0.7.dist-info/LICENSE
tuxput-0.0.7.dist-info/METADATA
tuxput-0.0.7.dist-info/WHEEL
tuxput-0.0.7.dist-info/entry_points.txt
tuxput-0.0.7.dist-info/top_level.txt
tuxput-0.0.7.dist-info/RECORD
