Metadata-Version: 2.1
Name: tuxput
Version: 0.0.7
Summary: The Serverless File Uploader
Home-page: https://gitlab.com/Linaro/tuxput
Author: Linaro Limited
Classifier: Development Status :: 3 - Alpha
Classifier: Environment :: Web Environment
Classifier: Framework :: Flask
Classifier: Intended Audience :: Developers
Classifier: Programming Language :: Python :: 3
Classifier: License :: OSI Approved :: MIT License
Classifier: Operating System :: OS Independent
Classifier: Topic :: Software Development :: Testing
Classifier: Topic :: System :: Operating System Kernels :: Linux
License-File: LICENSE
Requires-Dist: boto3
Requires-Dist: Flask
Requires-Dist: Click
